LICENSE
README.md
setup.cfg
setup.py
pihole_client/__init__.py
pihole_client/client.py
pihole_client/types.py
pihole_client.egg-info/PKG-INFO
pihole_client.egg-info/SOURCES.txt
pihole_client.egg-info/dependency_links.txt
pihole_client.egg-info/not-zip-safe
pihole_client.egg-info/requires.txt
pihole_client.egg-info/top_level.txt