Metadata-Version: 2.1
Name: pihole_client
Version: 1.0.0
Summary: Execute API calls to Pi-hole from python code
Home-page: https://github.com/ErilovNikita/pihole-client
Author-email: minitwiks@gmail.com
License: MIT
License-File: LICENSE
Requires-Dist: requests==2.32.3
Requires-Dist: urllib3==2.2.3
Requires-Dist: pydantic==2.9.2
